{
  "legislative_session": "104th",
  "identifier": "HB3503",
  "title": "CURRICULUM OVERVIEW&ALIGNMENT",
  "from_organization": "~{\"classification\": \"lower\"}",
  "classification": [
    "bill"
  ],
  "subject": [],
  "abstracts": [
    {
      "note": "",
      "abstract": "Creates the Illinois Curriculum Overview and Alignment Act. Requires, beginning January 1, 2026, the State Board of Education to conduct a comprehensive review of all mandated units of study every 5 years. Sets forth what the review shall include. Provides that the review process shall incorporate feedback from educators and administrators, parents and guardians, students, via surveys or focus groups, and subject matter experts and community organizations. Requires the State Board of Education to publish a public report summarizing findings and recommendations from the curriculum overview. Provides that following each curriculum overview, the State Board of Education shall: (1) develop an action plan to address identified gaps or areas for improvement; (2) provide professional development for educators on updates or changes; and (3) monitor the implementation of curriculum updates and assess their impact on student outcomes. Requires the General Assembly to appropriate funds necessary for the State Board of Education to carry out the requirements of the Act. Effective immediately."
    }
  ],
  "other_titles": [],
  "other_identifiers": [],
  "actions": [
    {
      "description": "Filed with the Clerk by Rep. Curtis J. Tarver, II",
      "date": "2025-02-07",
      "organization_id": "~{\"classification\": \"lower\"}",
      "classification": [
        "filing"
      ],
      "related_entities": []
    },
    {
      "description": "First Reading",
      "date": "2025-02-18",
      "organization_id": "~{\"classification\": \"lower\"}",
      "classification": [
        "reading-1"
      ],
      "related_entities": []
    },
    {
      "description": "Referred to Rules Committee",
      "date": "2025-02-18",
      "organization_id": "~{\"classification\": \"lower\"}",
      "classification": [],
      "related_entities": []
    },
    {
      "description": "Assigned to Education Policy Committee",
      "date": "2025-03-11",
      "organization_id": "~{\"classification\": \"lower\"}",
      "classification": [
        "referral-committee"
      ],
      "related_entities": []
    },
    {
      "description": "Do Pass / Short Debate Education Policy Committee;  009-004-000",
      "date": "2025-03-19",
      "organization_id": "~{\"classification\": \"lower\"}",
      "classification": [],
      "related_entities": []
    },
    {
      "description": "Placed on Calendar 2nd Reading - Short Debate",
      "date": "2025-03-19",
      "organization_id": "~{\"classification\": \"lower\"}",
      "classification": [
        "reading-2"
      ],
      "related_entities": []
    },
    {
      "description": "Second Reading - Short Debate",
      "date": "2025-03-26",
      "organization_id": "~{\"classification\": \"lower\"}",
      "classification": [
        "reading-2"
      ],
      "related_entities": []
    },
    {
      "description": "Held on Calendar Order of Second Reading - Short Debate",
      "date": "2025-03-26",
      "organization_id": "~{\"classification\": \"lower\"}",
      "classification": [
        "reading-2"
      ],
      "related_entities": []
    },
    {
      "description": "House Floor Amendment No. 1 Filed with Clerk by Rep. Curtis J. Tarver, II",
      "date": "2025-04-08",
      "organization_id": "~{\"classification\": \"lower\"}",
      "classification": [
        "amendment-introduction"
      ],
      "related_entities": []
    },
    {
      "description": "House Floor Amendment No. 1 Referred to Rules Committee",
      "date": "2025-04-08",
      "organization_id": "~{\"classification\": \"lower\"}",
      "classification": [],
      "related_entities": []
    },
    {
      "description": "House Floor Amendment No. 1 Rules Refers to Education Policy Committee",
      "date": "2025-04-08",
      "organization_id": "~{\"classification\": \"lower\"}",
      "classification": [],
      "related_entities": []
    },
    {
      "description": "House Floor Amendment No. 1 Recommends Be Adopted Education Policy Committee;  013-000-000",
      "date": "2025-04-09",
      "organization_id": "~{\"classification\": \"lower\"}",
      "classification": [
        "committee-passage-favorable"
      ],
      "related_entities": []
    },
    {
      "description": "House Floor Amendment No. 1 Adopted",
      "date": "2025-04-09",
      "organization_id": "~{\"classification\": \"lower\"}",
      "classification": [
        "amendment-passage"
      ],
      "related_entities": []
    },
    {
      "description": "Placed on Calendar Order of 3rd Reading - Short Debate",
      "date": "2025-04-09",
      "organization_id": "~{\"classification\": \"lower\"}",
      "classification": [],
      "related_entities": []
    },
    {
      "description": "Third Reading - Short Debate - Passed 116-000-000",
      "date": "2025-04-09",
      "organization_id": "~{\"classification\": \"lower\"}",
      "classification": [
        "passage",
        "reading-3"
      ],
      "related_entities": []
    },
    {
      "description": "Arrive in Senate",
      "date": "2025-04-10",
      "organization_id": "~{\"classification\": \"upper\"}",
      "classification": [
        "introduction"
      ],
      "related_entities": []
    },
    {
      "description": "Placed on Calendar Order of First Reading",
      "date": "2025-04-10",
      "organization_id": "~{\"classification\": \"upper\"}",
      "classification": [
        "reading-1"
      ],
      "related_entities": []
    },
    {
      "description": "Chief Senate Sponsor Sen. Lakesia Collins",
      "date": "2025-04-10",
      "organization_id": "~{\"classification\": \"upper\"}",
      "classification": [],
      "related_entities": []
    },
    {
      "description": "First Reading",
      "date": "2025-04-10",
      "organization_id": "~{\"classification\": \"upper\"}",
      "classification": [
        "reading-1"
      ],
      "related_entities": []
    },
    {
      "description": "Referred to Assignments",
      "date": "2025-04-10",
      "organization_id": "~{\"classification\": \"upper\"}",
      "classification": [],
      "related_entities": []
    },
    {
      "description": "Added Co-Sponsor Rep. Camille Y. Lilly",
      "date": "2025-04-10",
      "organization_id": "~{\"classification\": \"lower\"}",
      "classification": [],
      "related_entities": []
    },
    {
      "description": "Assigned to Education",
      "date": "2025-04-23",
      "organization_id": "~{\"classification\": \"upper\"}",
      "classification": [
        "referral-committee"
      ],
      "related_entities": []
    },
    {
      "description": "Rule 2-10 Committee Deadline Established As May 23, 2025",
      "date": "2025-05-09",
      "organization_id": "~{\"classification\": \"upper\"}",
      "classification": [],
      "related_entities": []
    },
    {
      "description": "Rule 2-10 Committee Deadline Established As June 1, 2025",
      "date": "2025-05-23",
      "organization_id": "~{\"classification\": \"upper\"}",
      "classification": [],
      "related_entities": []
    },
    {
      "description": "Rule 3-9(a) / Re-referred to Assignments",
      "date": "2025-06-02",
      "organization_id": "~{\"classification\": \"upper\"}",
      "classification": [],
      "related_entities": []
    }
  ],
  "sponsorships": [
    {
      "name": "Curtis J. Tarver, II",
      "classification": "primary",
      "entity_type": "person",
      "primary": true,
      "person_id": "~{\"chamber\": \"lower\", \"name\": \"Curtis J. Tarver, II\"}",
      "organization_id": null
    },
    {
      "name": "Camille Y. Lilly",
      "classification": "cosponsor",
      "entity_type": "person",
      "primary": false,
      "person_id": "~{\"chamber\": \"lower\", \"name\": \"Camille Y. Lilly\"}",
      "organization_id": null
    },
    {
      "name": "Lakesia Collins",
      "classification": "primary",
      "entity_type": "person",
      "primary": true,
      "person_id": "~{\"chamber\": \"upper\", \"name\": \"Lakesia Collins\"}",
      "organization_id": null
    }
  ],
  "related_bills": [],
  "versions": [
    {
      "note": "Introduced",
      "links": [
        {
          "url": "https://beta.ilga.gov/documents/legislation/104/HB/PDF/10400HB3503.pdf",
          "media_type": "application/pdf"
        },
        {
          "url": "https://beta.ilga.gov/Legislation/BillStatus/FullText?LegDocId=201969&DocName=10400HB3503&DocNum=3503&DocTypeID=HB&LegID=162181&GAID=18&SessionID=114&SpecSess=&Session=&Print=1",
          "media_type": "text/html"
        }
      ],
      "date": "",
      "classification": ""
    },
    {
      "note": "Engrossed",
      "links": [
        {
          "url": "https://beta.ilga.gov/documents/legislation/104/HB/PDF/10400HB3503eng.pdf",
          "media_type": "application/pdf"
        },
        {
          "url": "https://beta.ilga.gov/Legislation/BillStatus/FullText?LegDocId=201969&DocName=10400HB3503eng&DocNum=3503&DocTypeID=HB&LegID=162181&GAID=18&SessionID=114&SpecSess=&Session=&Print=1",
          "media_type": "text/html"
        }
      ],
      "date": "",
      "classification": ""
    },
    {
      "note": "House Amendment 001",
      "links": [
        {
          "url": "https://beta.ilga.gov/documents/legislation/104/HB/PDF/10400HB3503ham001.pdf",
          "media_type": "application/pdf"
        },
        {
          "url": "https://beta.ilga.gov/Legislation/BillStatus/FullText?LegDocId=204223&DocName=10400HB3503ham001&DocNum=3503&DocTypeID=HB&LegID=162181&GAID=18&SessionID=114&SpecSess=&Session=&Print=1",
          "media_type": "text/html"
        }
      ],
      "date": "",
      "classification": ""
    }
  ],
  "documents": [
    {
      "note": "Printer Friendly Version",
      "links": [
        {
          "url": "https://beta.ilga.gov/Legislation/BillStatus/FullText?GAID=18&DocNum=3503&DocTypeID=HB&LegId=162181&SessionID=114&Print=1",
          "media_type": ""
        }
      ],
      "date": "",
      "classification": ""
    }
  ],
  "citations": [],
  "sources": [
    {
      "url": "https://beta.ilga.gov/Legislation/BillStatus?DocNum=3503&GAID=18&DocTypeID=HB&LegId=162181&SessionID=114",
      "note": ""
    }
  ],
  "extras": {},
  "jurisdiction": {
    "id": "ocd-jurisdiction/country:us/state:il/government",
    "name": "Illinois",
    "classification": "state",
    "division_id": "ocd-division/country:us/state:il"
  },
  "scraped_at": "2025-06-20T17:37:31+00:00",
  "_id": "3e41c230-4dfd-11f0-8990-0a5235f7ee10"
}