{
  "legislative_session": "104th",
  "identifier": "HR234",
  "title": "ASSYRIAN AMERICAN HERITAGE MO.",
  "from_organization": "~{\"classification\": \"lower\"}",
  "classification": [
    "resolution"
  ],
  "subject": [],
  "abstracts": [
    {
      "note": "",
      "abstract": "Declares April 2025 as Assyrian American Heritage Month in the State of Illinois in celebration of the Assyrian American community. Recognizes the resilience, culture, and contributions of the Assyrian people and joins them in celebrating their rich heritage and the dawn of Assyrian New Year 6775."
    }
  ],
  "other_titles": [],
  "other_identifiers": [],
  "actions": [
    {
      "description": "Filed with the Clerk by Rep. Kevin John Olickal",
      "date": "2025-04-04",
      "organization_id": "~{\"classification\": \"lower\"}",
      "classification": [
        "filing"
      ],
      "related_entities": []
    },
    {
      "description": "Referred to Rules Committee",
      "date": "2025-04-07",
      "organization_id": "~{\"classification\": \"lower\"}",
      "classification": [],
      "related_entities": []
    },
    {
      "description": "Assigned to State Government Administration Committee",
      "date": "2025-04-22",
      "organization_id": "~{\"classification\": \"lower\"}",
      "classification": [
        "referral-committee"
      ],
      "related_entities": []
    },
    {
      "description": "Recommends Be Adopted State Government Administration Committee;  009-000-000",
      "date": "2025-04-30",
      "organization_id": "~{\"classification\": \"lower\"}",
      "classification": [
        "committee-passage-favorable"
      ],
      "related_entities": []
    },
    {
      "description": "Placed on Calendar Order of Resolutions",
      "date": "2025-05-01",
      "organization_id": "~{\"classification\": \"lower\"}",
      "classification": [],
      "related_entities": []
    },
    {
      "description": "Added Chief Co-Sponsor Rep. Hoan Huynh",
      "date": "2025-05-08",
      "organization_id": "~{\"classification\": \"lower\"}",
      "classification": [],
      "related_entities": []
    },
    {
      "description": "Resolution Adopted",
      "date": "2025-05-28",
      "organization_id": "~{\"classification\": \"lower\"}",
      "classification": [
        "passage"
      ],
      "related_entities": []
    }
  ],
  "sponsorships": [
    {
      "name": "Kevin John Olickal",
      "classification": "primary",
      "entity_type": "person",
      "primary": true,
      "person_id": "~{\"chamber\": \"lower\", \"name\": \"Kevin John Olickal\"}",
      "organization_id": null
    },
    {
      "name": "Hoan Huynh",
      "classification": "cosponsor",
      "entity_type": "person",
      "primary": false,
      "person_id": "~{\"chamber\": \"lower\", \"name\": \"Hoan Huynh\"}",
      "organization_id": null
    }
  ],
  "related_bills": [],
  "versions": [
    {
      "note": "Introduced",
      "links": [
        {
          "url": "https://beta.ilga.gov/documents/legislation/104/HR/PDF/10400HR0234.pdf",
          "media_type": "application/pdf"
        },
        {
          "url": "https://beta.ilga.gov/Legislation/BillStatus/FullText?LegDocId=204026&DocName=10400HR0234&DocNum=234&DocTypeID=HR&LegID=163421&GAID=18&SessionID=114&SpecSess=&Session=&Print=1",
          "media_type": "text/html"
        }
      ],
      "date": "",
      "classification": ""
    }
  ],
  "documents": [
    {
      "note": "Printer Friendly Version",
      "links": [
        {
          "url": "https://beta.ilga.gov/Legislation/BillStatus/FullText?GAID=18&DocNum=234&DocTypeID=HR&LegId=163421&SessionID=114&Print=1",
          "media_type": ""
        }
      ],
      "date": "",
      "classification": ""
    }
  ],
  "citations": [],
  "sources": [
    {
      "url": "https://beta.ilga.gov/Legislation/BillStatus?DocNum=234&GAID=18&DocTypeID=HR&LegId=163421&SessionID=114",
      "note": ""
    }
  ],
  "extras": {},
  "jurisdiction": {
    "id": "ocd-jurisdiction/country:us/state:il/government",
    "name": "Illinois",
    "classification": "state",
    "division_id": "ocd-division/country:us/state:il"
  },
  "scraped_at": "2025-06-20T17:38:00+00:00",
  "_id": "4fb222e4-4dfd-11f0-8990-0a5235f7ee10"
}