{
  "legislative_session": "104th",
  "identifier": "SB2002",
  "title": "ISP FUND CONSOLIDATION",
  "from_organization": "~{\"classification\": \"upper\"}",
  "classification": [
    "bill"
  ],
  "subject": [],
  "abstracts": [
    {
      "note": "",
      "abstract": "Amends the Illinois State Police Law, the State Finance Act, the Firearm Owners Identification Card Act, the Illinois Vehicle Code, the Criminal and Traffic Assessment Act, the Cannabis Control Act, the Illinois Controlled Substances Act, the Methamphetamine Control and Community Protection Act, the Narcotics Profit Forfeiture Act, the Unified Code of Corrections, the Sex Offender Registration Act, the Murderer and Violent Offender Against Youth Registration Act, and the Illinois False Claims Act. Makes changes to provisions concerning how certain moneys paid to the State are deposited into certain funds pertaining to the Illinois State Police. Provides that certain funds shall be dissolved after transferring the remaining balance in those funds to designated funds. Makes conforming changes. Effective September 1, 2026."
    }
  ],
  "other_titles": [],
  "other_identifiers": [],
  "actions": [
    {
      "description": "Filed with Secretary by Sen. Meg Loughran Cappel",
      "date": "2025-02-06",
      "organization_id": "~{\"classification\": \"upper\"}",
      "classification": [
        "filing"
      ],
      "related_entities": []
    },
    {
      "description": "First Reading",
      "date": "2025-02-06",
      "organization_id": "~{\"classification\": \"upper\"}",
      "classification": [
        "reading-1"
      ],
      "related_entities": []
    },
    {
      "description": "Referred to Assignments",
      "date": "2025-02-06",
      "organization_id": "~{\"classification\": \"upper\"}",
      "classification": [],
      "related_entities": []
    },
    {
      "description": "Added as Co-Sponsor Sen. Sally J. Turner",
      "date": "2025-02-19",
      "organization_id": "~{\"classification\": \"upper\"}",
      "classification": [],
      "related_entities": []
    },
    {
      "description": "Added as Co-Sponsor Sen. Linda Holmes",
      "date": "2025-02-19",
      "organization_id": "~{\"classification\": \"upper\"}",
      "classification": [],
      "related_entities": []
    },
    {
      "description": "Added as Co-Sponsor Sen. David Koehler",
      "date": "2025-02-19",
      "organization_id": "~{\"classification\": \"upper\"}",
      "classification": [],
      "related_entities": []
    },
    {
      "description": "Added as Co-Sponsor Sen. Michael E. Hastings",
      "date": "2025-02-20",
      "organization_id": "~{\"classification\": \"upper\"}",
      "classification": [],
      "related_entities": []
    },
    {
      "description": "Assigned to State Government",
      "date": "2025-03-12",
      "organization_id": "~{\"classification\": \"upper\"}",
      "classification": [
        "referral-committee"
      ],
      "related_entities": []
    },
    {
      "description": "Do Pass State Government;  009-000-000",
      "date": "2025-03-19",
      "organization_id": "~{\"classification\": \"upper\"}",
      "classification": [],
      "related_entities": []
    },
    {
      "description": "Placed on Calendar Order of 2nd Reading March 20, 2025",
      "date": "2025-03-19",
      "organization_id": "~{\"classification\": \"upper\"}",
      "classification": [
        "reading-2"
      ],
      "related_entities": []
    },
    {
      "description": "Second Reading",
      "date": "2025-03-20",
      "organization_id": "~{\"classification\": \"upper\"}",
      "classification": [
        "reading-2"
      ],
      "related_entities": []
    },
    {
      "description": "Placed on Calendar Order of 3rd Reading April 1, 2025",
      "date": "2025-03-20",
      "organization_id": "~{\"classification\": \"upper\"}",
      "classification": [],
      "related_entities": []
    },
    {
      "description": "Third Reading - Passed; 054-000-000",
      "date": "2025-04-03",
      "organization_id": "~{\"classification\": \"upper\"}",
      "classification": [
        "passage",
        "reading-3"
      ],
      "related_entities": []
    },
    {
      "description": "Arrived in House",
      "date": "2025-04-04",
      "organization_id": "~{\"classification\": \"lower\"}",
      "classification": [
        "introduction"
      ],
      "related_entities": []
    },
    {
      "description": "Chief House Sponsor Rep. John M. Cabello",
      "date": "2025-04-08",
      "organization_id": "~{\"classification\": \"lower\"}",
      "classification": [],
      "related_entities": []
    },
    {
      "description": "First Reading",
      "date": "2025-04-08",
      "organization_id": "~{\"classification\": \"lower\"}",
      "classification": [
        "reading-1"
      ],
      "related_entities": []
    },
    {
      "description": "Referred to Rules Committee",
      "date": "2025-04-08",
      "organization_id": "~{\"classification\": \"lower\"}",
      "classification": [],
      "related_entities": []
    },
    {
      "description": "Assigned to Executive Committee",
      "date": "2025-04-17",
      "organization_id": "~{\"classification\": \"lower\"}",
      "classification": [
        "referral-committee"
      ],
      "related_entities": []
    },
    {
      "description": "House Committee Amendment No. 1 Filed with Clerk by Rep. John M. Cabello",
      "date": "2025-04-21",
      "organization_id": "~{\"classification\": \"lower\"}",
      "classification": [
        "amendment-introduction"
      ],
      "related_entities": []
    },
    {
      "description": "House Committee Amendment No. 1 Referred to Rules Committee",
      "date": "2025-04-21",
      "organization_id": "~{\"classification\": \"lower\"}",
      "classification": [],
      "related_entities": []
    },
    {
      "description": "House Committee Amendment No. 1 Rules Refers to Executive Committee",
      "date": "2025-04-22",
      "organization_id": "~{\"classification\": \"lower\"}",
      "classification": [],
      "related_entities": []
    },
    {
      "description": "Do Pass / Short Debate Executive Committee;  011-000-000",
      "date": "2025-04-23",
      "organization_id": "~{\"classification\": \"lower\"}",
      "classification": [],
      "related_entities": []
    },
    {
      "description": "House Committee Amendment No. 1 Tabled",
      "date": "2025-04-23",
      "organization_id": "~{\"classification\": \"lower\"}",
      "classification": [
        "amendment-failure"
      ],
      "related_entities": []
    },
    {
      "description": "Placed on Calendar 2nd Reading - Short Debate",
      "date": "2025-04-23",
      "organization_id": "~{\"classification\": \"lower\"}",
      "classification": [
        "reading-2"
      ],
      "related_entities": []
    },
    {
      "description": "Second Reading - Short Debate",
      "date": "2025-05-14",
      "organization_id": "~{\"classification\": \"lower\"}",
      "classification": [
        "reading-2"
      ],
      "related_entities": []
    },
    {
      "description": "Placed on Calendar Order of 3rd Reading - Short Debate",
      "date": "2025-05-14",
      "organization_id": "~{\"classification\": \"lower\"}",
      "classification": [],
      "related_entities": []
    },
    {
      "description": "Third Reading - Short Debate - Passed 114-000-000",
      "date": "2025-05-22",
      "organization_id": "~{\"classification\": \"lower\"}",
      "classification": [
        "passage",
        "reading-3"
      ],
      "related_entities": []
    },
    {
      "description": "Passed Both Houses",
      "date": "2025-05-22",
      "organization_id": "~{\"classification\": \"upper\"}",
      "classification": [],
      "related_entities": []
    }
  ],
  "sponsorships": [
    {
      "name": "Meg Loughran Cappel",
      "classification": "primary",
      "entity_type": "person",
      "primary": true,
      "person_id": "~{\"chamber\": \"upper\", \"name\": \"Meg Loughran Cappel\"}",
      "organization_id": null
    },
    {
      "name": "Sally J. Turner",
      "classification": "cosponsor",
      "entity_type": "person",
      "primary": false,
      "person_id": "~{\"chamber\": \"upper\", \"name\": \"Sally J. Turner\"}",
      "organization_id": null
    },
    {
      "name": "Linda Holmes",
      "classification": "cosponsor",
      "entity_type": "person",
      "primary": false,
      "person_id": "~{\"chamber\": \"upper\", \"name\": \"Linda Holmes\"}",
      "organization_id": null
    },
    {
      "name": "David Koehler",
      "classification": "cosponsor",
      "entity_type": "person",
      "primary": false,
      "person_id": "~{\"chamber\": \"upper\", \"name\": \"David Koehler\"}",
      "organization_id": null
    },
    {
      "name": "Michael E. Hastings",
      "classification": "cosponsor",
      "entity_type": "person",
      "primary": false,
      "person_id": "~{\"chamber\": \"upper\", \"name\": \"Michael E. Hastings\"}",
      "organization_id": null
    },
    {
      "name": "John M. Cabello",
      "classification": "primary",
      "entity_type": "person",
      "primary": true,
      "person_id": "~{\"chamber\": \"lower\", \"name\": \"John M. Cabello\"}",
      "organization_id": null
    }
  ],
  "related_bills": [],
  "versions": [
    {
      "note": "Introduced",
      "links": [
        {
          "url": "https://beta.ilga.gov/documents/legislation/104/SB/PDF/10400SB2002.pdf",
          "media_type": "application/pdf"
        },
        {
          "url": "https://beta.ilga.gov/Legislation/BillStatus/FullText?LegDocId=201194&DocName=10400SB2002&DocNum=2002&DocTypeID=SB&LegID=161406&GAID=18&SessionID=114&SpecSess=&Session=&Print=1",
          "media_type": "text/html"
        }
      ],
      "date": "",
      "classification": ""
    },
    {
      "note": "Engrossed",
      "links": [
        {
          "url": "https://beta.ilga.gov/documents/legislation/104/SB/PDF/10400SB2002eng.pdf",
          "media_type": "application/pdf"
        },
        {
          "url": "https://beta.ilga.gov/Legislation/BillStatus/FullText?LegDocId=201194&DocName=10400SB2002eng&DocNum=2002&DocTypeID=SB&LegID=161406&GAID=18&SessionID=114&SpecSess=&Session=&Print=1",
          "media_type": "text/html"
        }
      ],
      "date": "",
      "classification": ""
    },
    {
      "note": "Enrolled",
      "links": [
        {
          "url": "https://beta.ilga.gov/documents/legislation/104/SB/PDF/10400SB2002enr.pdf",
          "media_type": "application/pdf"
        },
        {
          "url": "https://beta.ilga.gov/Legislation/BillStatus/FullText?LegDocId=201194&DocName=10400SB2002enr&DocNum=2002&DocTypeID=SB&LegID=161406&GAID=18&SessionID=114&SpecSess=&Session=&Print=1",
          "media_type": "text/html"
        }
      ],
      "date": "",
      "classification": ""
    },
    {
      "note": "House Amendment 001",
      "links": [
        {
          "url": "https://beta.ilga.gov/documents/legislation/104/SB/PDF/10400SB2002ham001.pdf",
          "media_type": "application/pdf"
        },
        {
          "url": "https://beta.ilga.gov/Legislation/BillStatus/FullText?LegDocId=204369&DocName=10400SB2002ham001&DocNum=2002&DocTypeID=SB&LegID=161406&GAID=18&SessionID=114&SpecSess=&Session=&Print=1",
          "media_type": "text/html"
        }
      ],
      "date": "",
      "classification": ""
    }
  ],
  "documents": [
    {
      "note": "Printer Friendly Version",
      "links": [
        {
          "url": "https://beta.ilga.gov/Legislation/BillStatus/FullText?GAID=18&DocNum=2002&DocTypeID=SB&LegId=161406&SessionID=114&Print=1",
          "media_type": ""
        }
      ],
      "date": "",
      "classification": ""
    }
  ],
  "citations": [],
  "sources": [
    {
      "url": "https://beta.ilga.gov/Legislation/BillStatus?DocNum=2002&GAID=18&DocTypeID=SB&LegId=161406&SessionID=114",
      "note": ""
    }
  ],
  "extras": {},
  "jurisdiction": {
    "id": "ocd-jurisdiction/country:us/state:il/government",
    "name": "Illinois",
    "classification": "state",
    "division_id": "ocd-division/country:us/state:il"
  },
  "scraped_at": "2025-06-20T17:39:35+00:00",
  "_id": "87d7b5d0-4dfd-11f0-8990-0a5235f7ee10"
}